zenossapi/__init__.py
zenossapi/apiclient.py
zenossapi/routers/__init__.py
zenossapi/routers/device.py
zenossapi/routers/devicemanagement.py
zenossapi/routers/events.py
zenossapi/routers/jobs.py
zenossapi/routers/monitor.py
zenossapi/routers/properties.py
zenossapi/routers/template.py
ZenossAPIClient-0.2.7.dist-info/LICENSE.txt
ZenossAPIClient-0.2.7.dist-info/METADATA
ZenossAPIClient-0.2.7.dist-info/WHEEL
ZenossAPIClient-0.2.7.dist-info/top_level.txt
ZenossAPIClient-0.2.7.dist-info/RECORD
