Metadata-Version: 2.1
Name: ZenossAPIClient
Version: 0.2.7
Summary: Zenoss API client module
Home-page: https://github.com/Zuora-TechOps/ZenossAPIClient
Author: Mark Troyer
Author-email: disco@zuora.com
License: Apache
Keywords: Zenoss monitoring api
Platform: UNKNOWN
Classifier: Intended Audience :: System Administrators
Classifier: License :: OSI Approved :: Apache Software License
Classifier: Natural Language :: English
Classifier: Programming Language :: Python :: 2
Classifier: Programming Language :: Python :: 2.7
Classifier: Topic :: System :: Monitoring
Requires-Dist: python-dateutil (>=2.6.1)
Requires-Dist: requests (>=2.18.1)
